{
	"frames": {
		"back": {
			"frame": {
				"x": 1,
				"y": 1,
				"w": 195,
				"h": 499
			},
			"rotated": false,
			"trimmed": false,
			"spriteSourceSize": {
				"x": 0,
				"y": 0,
				"w": 195,
				"h": 499
			},
			"sourceSize": {
				"w": 195,
				"h": 499
			}
		},
		"front": {
			"frame": {
				"x": 198,
				"y": 1,
				"w": 184,
				"h": 483
			},
			"rotated": false,
			"trimmed": false,
			"spriteSourceSize": {
				"x": 0,
				"y": 0,
				"w": 184,
				"h": 483
			},
			"sourceSize": {
				"w": 184,
				"h": 483
			}
		},
		"left": {
			"frame": {
				"x": 384,
				"y": 1,
				"w": 155,
				"h": 495
			},
			"rotated": false,
			"trimmed": false,
			"spriteSourceSize": {
				"x": 0,
				"y": 0,
				"w": 155,
				"h": 495
			},
			"sourceSize": {
				"w": 155,
				"h": 495
			}
		},
		"right": {
			"frame": {
				"x": 541,
				"y": 1,
				"w": 155,
				"h": 495
			},
			"rotated": false,
			"trimmed": false,
			"spriteSourceSize": {
				"x": 0,
				"y": 0,
				"w": 155,
				"h": 495
			},
			"sourceSize": {
				"w": 155,
				"h": 495
			}
		},
		"smile": {
			"frame": {
				"x": 698,
				"y": 1,
				"w": 195,
				"h": 483
			},
			"rotated": false,
			"trimmed": false,
			"spriteSourceSize": {
				"x": 0,
				"y": 0,
				"w": 195,
				"h": 483
			},
			"sourceSize": {
				"w": 195,
				"h": 483
			}
		},
		"smile_2": {
			"frame": {
				"x": 895,
				"y": 1,
				"w": 221,
				"h": 474
			},
			"rotated": false,
			"trimmed": false,
			"spriteSourceSize": {
				"x": 0,
				"y": 0,
				"w": 221,
				"h": 474
			},
			"sourceSize": {
				"w": 221,
				"h": 474
			}
		}
	},
	"meta": {
		"app": "http://www.codeandweb.com/texturepacker",
		"version": "1.0",
		"image": "spritesheet.png",
		"format": "RGBA8888",
		"size": {
			"w": 1117,
			"h": 501
		},
		"scale": "1"
	}
}